kognitos/bdk/runtime/__init__.py
kognitos/bdk/runtime/client/__init__.py
kognitos/bdk/runtime/client/base.py
kognitos/bdk/runtime/client/base_transport.py
kognitos/bdk/runtime/client/book_authentication_descriptor.py
kognitos/bdk/runtime/client/book_descriptor.py
kognitos/bdk/runtime/client/book_procedure_descriptor.py
kognitos/bdk/runtime/client/book_procedure_signature.py
kognitos/bdk/runtime/client/client.py
kognitos/bdk/runtime/client/concept_descriptor.py
kognitos/bdk/runtime/client/concept_type.py
kognitos/bdk/runtime/client/concept_value.py
kognitos/bdk/runtime/client/configs.py
kognitos/bdk/runtime/client/connection_required.py
kognitos/bdk/runtime/client/credential_descriptor.py
kognitos/bdk/runtime/client/discoverable.py
kognitos/bdk/runtime/client/environment_information.py
kognitos/bdk/runtime/client/example_descriptor.py
kognitos/bdk/runtime/client/exceptions.py
kognitos/bdk/runtime/client/expression.py
kognitos/bdk/runtime/client/grpc_transport.py
kognitos/bdk/runtime/client/http_transport.py
kognitos/bdk/runtime/client/input_concept.py
kognitos/bdk/runtime/client/input_mappers/__init__.py
kognitos/bdk/runtime/client/input_mappers/answered_question.py
kognitos/bdk/runtime/client/input_mappers/authentication.py
kognitos/bdk/runtime/client/input_mappers/expression.py
kognitos/bdk/runtime/client/input_mappers/input_concepts.py
kognitos/bdk/runtime/client/input_mappers/noun_phrase.py
kognitos/bdk/runtime/client/input_mappers/offload.py
kognitos/bdk/runtime/client/input_mappers/promise.py
kognitos/bdk/runtime/client/input_mappers/value.py
kognitos/bdk/runtime/client/lambda_rie_transport.py
kognitos/bdk/runtime/client/lambda_transport.py
kognitos/bdk/runtime/client/mappers/__init__.py
kognitos/bdk/runtime/client/mappers/book_authentication_descriptor.py
kognitos/bdk/runtime/client/mappers/book_descriptor.py
kognitos/bdk/runtime/client/mappers/book_procedure_descriptor.py
kognitos/bdk/runtime/client/mappers/book_procedure_signature.py
kognitos_bdk_runtime_client-1.37.0.dist-info/LICENSE
kognitos_bdk_runtime_client-1.37.0.dist-info/METADATA
kognitos_bdk_runtime_client-1.37.0.dist-info/WHEEL
kognitos_bdk_runtime_client-1.37.0.dist-info/entry_points.txt
kognitos_bdk_runtime_client-1.37.0.dist-info/RECORD
