Metadata-Version: 2.1
Name: kognitos-bdk-runtime-client
Version: 1.37.0
Summary: Kognitos Book Runtime Client
License: Proprietary
Author: Emiliano Lesende
Author-email: emiliano@kognitos.com
Requires-Python: >=3.9,<4.0
Classifier: License :: Other/Proprietary License
Classifier: Programming Language :: Python :: 3
Classifier: Programming Language :: Python :: 3.9
Classifier: Programming Language :: Python :: 3.10
Classifier: Programming Language :: Python :: 3.11
Classifier: Programming Language :: Python :: 3.12
Requires-Dist: boto3 (>=1.24.96,<2.0.0)
Requires-Dist: grpcio (==1.68.1)
Requires-Dist: protobuf (>=4.25,<5.0)
Requires-Dist: requests (>=2.31.0,<3.0.0)
